{
  "type": "meatmaster:meat_compactor",
  "ingredients": [
    {
      "item": "minecraft:tropical_fish"
    },
    {
      "item": "minecraft:tropical_fish"
    },
    {
      "item": "minecraft:tropical_fish"
    },
    {
      "item": "minecraft:tropical_fish"
    },
    {
      "item": "minecraft:tropical_fish"
    },
    {
      "item": "minecraft:tropical_fish"
    },
    {
      "item": "minecraft:tropical_fish"
    },
    {
      "item": "minecraft:tropical_fish"
    },
    {
      "item": "minecraft:tropical_fish"
    }
  ],
  "result": {
    "item": "meatmaster:tropical_fish_block"
  }
}